m_lib_defenc-1.1.1-py2.7-nspkg.pth
m_lib/defenc.py
m_lib_defenc-1.1.1.dist-info/METADATA
m_lib_defenc-1.1.1.dist-info/RECORD
m_lib_defenc-1.1.1.dist-info/WHEEL
m_lib_defenc-1.1.1.dist-info/namespace_packages.txt
m_lib_defenc-1.1.1.dist-info/top_level.txt
